pyadaptivecard/__init__.py
pyadaptivecard/test/__init__.py
pymsteamsadaptivecard-0.5.0.dist-info/licenses/LICENCE.txt
pymsteamsadaptivecard-0.5.0.dist-info/METADATA
pymsteamsadaptivecard-0.5.0.dist-info/WHEEL
pymsteamsadaptivecard-0.5.0.dist-info/top_level.txt
pymsteamsadaptivecard-0.5.0.dist-info/RECORD
