Metadata-Version: 2.4
Name: PyMsTeamsAdaptiveCard
Version: 0.5.0
Summary: Generate Microsoft Teams Adaptive Cards for new Connectors
Home-page: http://pypi.python.org/pypi/PyMsTeamsAdaptiveCard/
Author: Florian Salaun
Author-email: florian.salaun@gmail.com
License: LICENSE.txt
License-File: LICENCE.txt
Requires-Dist: requests>=2.20.0
Dynamic: author
Dynamic: author-email
Dynamic: description
Dynamic: description-content-type
Dynamic: home-page
Dynamic: license
Dynamic: license-file
Dynamic: requires-dist
Dynamic: summary
